polars_opt/__init__.py
polars_opt/main.py
polars_optimization-0.1.0.dist-info/METADATA
polars_optimization-0.1.0.dist-info/WHEEL
polars_optimization-0.1.0.dist-info/RECORD
